aniachi/__init__.py
aniachi/stringUtils.py
aniachi/systemUtils.py
aniachi/test.py
aniachi/timeUtils.py
py_common_fetch-0.375.data/scripts/stringUtils.py
py_common_fetch-0.375.data/scripts/systemUtils.py
py_common_fetch-0.375.data/scripts/timeUtils.py
py_common_fetch-0.375.dist-info/METADATA
py_common_fetch-0.375.dist-info/WHEEL
py_common_fetch-0.375.dist-info/top_level.txt
py_common_fetch-0.375.dist-info/RECORD
