Metadata-Version: 2.1
Name: py_common_fetch
Version: 0.375
Summary: A really simple to use Python fetch screen
Home-page: https://github.com/bygregonline/py-common-fetch
Author: Greg flores
Author-email: bygregonline@yahoo.com
License: MIT
Keywords: noefetch common information welcome screen
Requires-Dist: pip
Requires-Dist: psutil>=5.4.5
Requires-Dist: json2html
Requires-Dist: py-cpuinfo
Requires-Dist: termcolor
Requires-Dist: numpy
Requires-Dist: tabulate
